alu_8bit.v
module alu_8bit(output reg [7:0]r,input [7:0]a,input [7:0]b,input [1:0]ms,input [1:0]ss);
reg [7:0] ar,lr,sr;
always @(*)
begin
case (ss)
2'b00:ar <= a+b;
2'b01:ar <= a-b;
2'b10:ar <= a+1;
2'b11:ar <= a-1;
endcase
case (ss)
2'b00:lr <= a&b;
2'b01:lr <= a|b;
2'b10:lr <= a^b;
2'b11:lr <= ~a;
endcase
case (ss)
2'b00:sr <= a<<1;
2'b01:sr <= a>>1;
endcase
case (ms)
2'b00:r <= ar;
2'b01:r <= lr;
2'b10:r <= sr;
2'b11:r <= 8'b00000000;
endcase
end
endmodule

tb_alu_8bit.v
module tb_alu_8bit;

reg  [7:0] a, b;
reg  [1:0] ms, ss;
wire [7:0] r;

alu_8bit uut (r,a,b,ms,ss);

initial
begin
    $dumpfile("alu_8bit.vcd");
    $dumpvars(0, tb_alu_8bit);
    a = 8'd10; 
    b = 8'd5;
    ms = 2'b00; ss = 2'b00; #10;
    ms = 2'b00; ss = 2'b01; #10;
    ms = 2'b00; ss = 2'b10; #10;
    ms = 2'b00; ss = 2'b11; #10;
    ms = 2'b01; ss = 2'b00; #10;
    ms = 2'b01; ss = 2'b01; #10;
    ms = 2'b01; ss = 2'b10; #10;
    ms = 2'b01; ss = 2'b11; #10;
    ms = 2'b10; ss = 2'b00; #10; 
    ms = 2'b10; ss = 2'b01; #10;
    $finish;
end
endmodule

alu_8bit.vcd
$date
	Sun Feb 22 06:59:38 2026
$end
$version
	Icarus Verilog
$end
$timescale
	1s
$end
$scope module tb_alu_8bit $end
$var wire 8 ! r [7:0] $end
$var reg 8 " a [7:0] $end
$var reg 8 # b [7:0] $end
$var reg 2 $ ms [1:0] $end
$var reg 2 % ss [1:0] $end
$scope module uut $end
$var wire 8 & a [7:0] $end
$var wire 8 ' b [7:0] $end
$var wire 2 ( ms [1:0] $end
$var wire 2 ) ss [1:0] $end
$var reg 8 * ar [7:0] $end
$var reg 8 + lr [7:0] $end
$var reg 8 , r [7:0] $end
$var reg 8 - sr [7:0] $end
$upscope $end
$upscope $end
$enddefinitions $end
$comment Show the parameter values. $end
$dumpall
$end
#0
$dumpvars
b10100 -
b1111 ,
b0 +
b1111 *
b0 )
b0 (
b101 '
b1010 &
b0 %
b0 $
b101 #
b1010 "
b1111 !
$end
#10
b101 !
b101 ,
b101 -
b1111 +
b101 *
b1 %
b1 )
#20
b1011 !
b1011 ,
b1011 *
b10 %
b10 )
#30
b1001 !
b1001 ,
b11110101 +
b1001 *
b11 %
b11 )
#40
b0 !
b0 ,
b10100 -
b0 +
b1111 *
b0 %
b0 )
b1 $
b1 (
#50
b1111 !
b1111 ,
b101 -
b1111 +
b101 *
b1 %
b1 )
#60
b1011 *
b10 %
b10 )
#70
b11110101 !
b11110101 ,
b11110101 +
b1001 *
b11 %
b11 )
#80
b10100 !
b10100 ,
b10100 -
b0 +
b1111 *
b0 %
b0 )
b10 $
b10 (
#90
b101 !
b101 ,
b101 -
b1111 +
b101 *
b1 %
b1 )
