3to8_decoder/decoder_3to8.v
module decoder_3to8 (input [2:0]i,output [7:0]d);
assign d[0]=(~i[2])&(~i[1])&(~i[0]);
assign d[1]=(~i[2])&(~i[1])&(i[0]);
assign d[2]=(~i[2])&(i[1])&(~i[0]);
assign d[3]=(~i[2])&(i[1])&(i[0]);
assign d[4]=(i[2])&(~i[1])&(~i[0]);
assign d[5]=(i[2])&(~i[1])&(i[0]);
assign d[6]=(i[2])&(i[1])&(~i[0]);
assign d[7]=(i[2])&(i[1])&(i[0]);

endmodule

3to8_decoder/tb_decoder_3to8.v
module tb_decoder_3to8;
reg [2:0]i;
wire [7:0]d;
decoder_3to8 de(i,d);
initial begin
    $dumpfile("tb_decoder_3to8.vcd");
    $dumpvars(0, tb_decoder_3to8);
    i=3'b000;
    #100 i=3'b001;
    #100 i=3'b010;
    #100 i=3'b011;
    #100 i=3'b100;
    #100 i=3'b101;
    #100 i=3'b110;
    #100 i=3'b111;
    #100 $finish;
end
initial
begin
    $monitor("time = %t i = %b d = %b",$time,i,d);
end
endmodule

3to8_decoder/tb_decoder_3to8.vcd
$date
	Wed Feb 11 04:18:46 2026
$end
$version
	Icarus Verilog
$end
$timescale
	1s
$end
$scope module tb_decoder_3to8 $end
$var wire 8 ! d [7:0] $end
$var reg 3 " i [2:0] $end
$scope module de $end
$var wire 3 # i [2:0] $end
$var wire 8 $ d [7:0] $end
$upscope $end
$upscope $end
$enddefinitions $end
$comment Show the parameter values. $end
$dumpall
$end
#0
$dumpvars
b1 $
b0 #
b0 "
b1 !
$end
#100
b10 !
b10 $
b1 "
b1 #
#200
b100 !
b100 $
b10 "
b10 #
#300
b1000 !
b1000 $
b11 "
b11 #
#400
b10000 !
b10000 $
b100 "
b100 #
#500
b100000 !
b100000 $
b101 "
b101 #
#600
b1000000 !
b1000000 $
b110 "
b110 #
#700
b10000000 !
b10000000 $
b111 "
b111 #
